{
  "6282238228919": {
    "name": "Raja Ngawi",
    "leader": "6282238228919",
    "anggota": [
      "6285284006210",
      "6281274619889",
      "6285129531056"
    ],
    "level": 1,
    "exp": 0,
    "created": 1762853391086
  },
  "6281339218514": {
    "name": "kesatria baja hitam",
    "leader": "6281339218514",
    "anggota": [],
    "level": 1,
    "exp": 0,
    "created": 1762920059829
  },
  "6289699912064": {
    "name": "vin",
    "leader": "6289699912064",
    "anggota": [],
    "level": 1,
    "exp": 0,
    "created": 1764149700030
  },
  "6283178684258": {
    "name": "fallzzz2gd",
    "leader": "6283178684258",
    "anggota": [
      "6285863508438"
    ],
    "level": 1,
    "exp": 0,
    "created": 1767157009224
  },
  "6283840508632": {
    "name": "VALOUR",
    "leader": "6283840508632",
    "anggota": [],
    "level": 1,
    "exp": 0,
    "created": 1767588245358
  },
  "6283870289807": {
    "name": "De Valour's",
    "leader": "6283870289807",
    "anggota": [],
    "level": 1,
    "exp": 0,
    "created": 1768135960392
  },
  "6285188322188": {
    "name": "*Asgard*",
    "leader": "6285188322188",
    "anggota": [],
    "level": 1,
    "exp": 0,
    "created": 1768135996984
  }
}